<?xml version="1.0" encoding="utf-8" ?>
<dwsync>
<file name="icon1.png" server="134.209.98.237/public/webtest/" local="132042064800127853" remote="132103132790000000" Dst="0" />
<file name="icon2.png" server="134.209.98.237/public/webtest/" local="132042064800147801" remote="132103132800000000" Dst="0" />
<file name="icon3.png" server="134.209.98.237/public/webtest/" local="132042064800177750" remote="132103132800000000" Dst="0" />
<file name="images1.jpg" server="134.209.98.237/public/webtest/" local="132042064800217612" remote="132103132810000000" Dst="0" />
<file name="images12.jpg" server="134.209.98.237/public/webtest/" local="132042064800347264" remote="132103132830000000" Dst="0" />
<file name="images13.jpg" server="134.209.98.237/public/webtest/" local="132042064800377350" remote="132103132840000000" Dst="0" />
<file name="LOGO.jpg" server="134.209.98.237/public/webtest/" local="132042064800077984" remote="132103132840000000" Dst="0" />
<file name="onofflink.png" server="134.209.98.237/public/webtest/" local="132042064800417076" remote="132103132850000000" Dst="0" />
<file name="PARTNER.jpg" server="134.209.98.237/public/webtest/" local="132042064800097955" remote="132103132860000000" Dst="0" />
<file name="PARTNER_UP.png" server="134.209.98.237/public/webtest/" local="132042064800117894" remote="132103132870000000" Dst="0" />
</dwsync>